README.rst
setup.py
discordcalendarbot/__init__.py
discordcalendarbot/__main__.py
discordcalendarbot/conf.py
discordcalendarbot.egg-info/PKG-INFO
discordcalendarbot.egg-info/SOURCES.txt
discordcalendarbot.egg-info/dependency_links.txt
discordcalendarbot.egg-info/requires.txt
discordcalendarbot.egg-info/top_level.txt