Metadata-Version: 1.0
Name: discordcalendarbot
Version: 1.0.1
Summary: Discord bot that handle a Google calendar
Home-page: https://github.com/johndacost/PyBot
Author: Axel Rieben & Johnny Da Costa
Author-email: axel.rieben@he-arc.ch, johnny.dacosta@he-arc.ch
License: MIT
Keywords: discord,asyncio,bot,google calendar
Platform: UNKNOWN
